dmapiclient/__init__.py
dmapiclient/antivirus.py
dmapiclient/audit.py
dmapiclient/base.py
dmapiclient/data.py
dmapiclient/errors.py
dmapiclient/exceptions.py
dmapiclient/py.typed
dmapiclient/search.py
digitalmarketplace_apiclient-24.0.0.dist-info/LICENCE
digitalmarketplace_apiclient-24.0.0.dist-info/METADATA
digitalmarketplace_apiclient-24.0.0.dist-info/WHEEL
digitalmarketplace_apiclient-24.0.0.dist-info/top_level.txt
digitalmarketplace_apiclient-24.0.0.dist-info/RECORD
