Metadata-Version: 2.1
Name: digitalmarketplace-apiclient
Version: 24.0.0
Summary: Digital Marketplace Data and Search API clients
Home-page: https://github.com/alphagov/digitalmarketplace-apiclient
Author: GDS Developers
License: MIT
Platform: UNKNOWN
Requires-Python: ~=3.9
License-File: LICENCE
Requires-Dist: requests (<3,>=2.18.4)
